logavu/__about__.py
logavu/__init__.py
logavu/__main__.py
logavu/cli.py
logavu/main.py
logavu/flutter_assets/.last_build_id
logavu/flutter_assets/AssetManifest.json
logavu/flutter_assets/AssetManifest.smcbin
logavu/flutter_assets/Engine.json
logavu/flutter_assets/FontManifest.json
logavu/flutter_assets/NOTICES.Z
logavu/flutter_assets/isolate_snapshot_data
logavu/flutter_assets/kernel_blob.bin
logavu/flutter_assets/vm_snapshot_data
logavu/flutter_assets/fonts/MaterialIcons-Regular.otf
logavu/flutter_assets/packages/cupertino_icons/assets/CupertinoIcons.ttf
logavu/flutter_assets/shaders/ink_sparkle.frag
logavu-0.1.1.dist-info/METADATA
logavu-0.1.1.dist-info/WHEEL
logavu-0.1.1.dist-info/entry_points.txt
logavu-0.1.1.dist-info/licenses/LICENSE
logavu-0.1.1.dist-info/RECORD
