Metadata-Version: 2.1
Name: logavu
Version: 0.1.1
Project-URL: Documentation, https://github.com/crungelab/logavu#readme
Project-URL: Issues, https://github.com/crungelab/logavu/issues
Project-URL: Source, https://github.com/crungelab/logavu
Author-email: Kurtis Fields <kurtisfields@gmail.com>
License-Expression: MIT
License-File: LICENSE
Classifier: Development Status :: 4 - Beta
Classifier: Programming Language :: Python
Classifier: Programming Language :: Python :: 3.8
Classifier: Programming Language :: Python :: 3.9
Classifier: Programming Language :: Python :: 3.10
Classifier: Programming Language :: Python :: 3.11
Classifier: Programming Language :: Python :: Implementation :: CPython
Classifier: Programming Language :: Python :: Implementation :: PyPy
Requires-Python: >=3.8
Requires-Dist: attacus==0.1.5
Requires-Dist: click~=8.1.3
Requires-Dist: loguru~=0.7.0
Requires-Dist: python-dotenv~=1.0.0
